flex_gw_api_automation/__init__.py
flex_gw_api_automation/anypoint_platform/__init__.py
flex_gw_api_automation/anypoint_platform/access_management.py
flex_gw_api_automation/anypoint_platform/api_manager.py
flex_gw_api_automation/anypoint_platform/entities.py
flex_gw_api_automation/config_schema.yaml
flex_gw_api_automation/flex_gw.py
flex_gw_api_automation-0.1.9.dist-info/METADATA
flex_gw_api_automation-0.1.9.dist-info/WHEEL
flex_gw_api_automation-0.1.9.dist-info/RECORD
