Metadata-Version: 2.1
Name: flex-gw-api-automation
Version: 0.1.9
Summary: 
Author: Damian Calabresi
Author-email: dcalabresi@salesforce.com
Requires-Python: >=3.11,<4.0
Classifier: Programming Language :: Python :: 3
Classifier: Programming Language :: Python :: 3.11
Classifier: Programming Language :: Python :: 3.12
Classifier: Programming Language :: Python :: 3.13
Requires-Dist: pyyaml (==6.0.2)
Requires-Dist: requests (==2.32.3)
Requires-Dist: yamale (==5.2.1)
